ml_recsys_tools/__init__.py
ml_recsys_tools/data_handlers/__init__.py
ml_recsys_tools/data_handlers/interaction_handlers_base.py
ml_recsys_tools/data_handlers/interactions_with_features.py
ml_recsys_tools/datasets/__init__.py
ml_recsys_tools/datasets/prep_movielense_data.py
ml_recsys_tools/evaluation/__init__.py
ml_recsys_tools/evaluation/ranks_scoring.py
ml_recsys_tools/recommenders/__init__.py
ml_recsys_tools/recommenders/combination_ensembles.py
ml_recsys_tools/recommenders/cooccurrence_recommenders.py
ml_recsys_tools/recommenders/ensembles_base.py
ml_recsys_tools/recommenders/factorisation_clustering.py
ml_recsys_tools/recommenders/factorization_base.py
ml_recsys_tools/recommenders/implib_recommenders.py
ml_recsys_tools/recommenders/lightfm_recommender.py
ml_recsys_tools/recommenders/recommender_base.py
ml_recsys_tools/recommenders/regression_recommenders.py
ml_recsys_tools/recommenders/similarity_recommenders.py
ml_recsys_tools/recommenders/subdivision_ensembles.py
ml_recsys_tools/utils/__init__.py
ml_recsys_tools/utils/instrumentation.py
ml_recsys_tools/utils/logging_config.py
ml_recsys_tools/utils/pandas_utils.py
ml_recsys_tools/utils/parallelism.py
ml_recsys_tools/utils/similarity.py
ml_recsys_tools/utils/sklearn_extenstions.py
ml_recsys_tools/utils/testing.py
ml_recsys_tools-0.9.1.dist-info/LICENSE
ml_recsys_tools-0.9.1.dist-info/METADATA
ml_recsys_tools-0.9.1.dist-info/WHEEL
ml_recsys_tools-0.9.1.dist-info/top_level.txt
ml_recsys_tools-0.9.1.dist-info/RECORD
