Metadata-Version: 2.1
Name: ml-recsys-tools
Version: 0.9.1
Summary: Tools for recommendation systems development
Home-page: https://github.com/artdgn/ml-recsys-tools
Author: Arthur Deygin
Author-email: arthurdgn@gmail.com
License: UNKNOWN
Keywords: recommendations machine learning
Platform: UNKNOWN
Classifier: Development Status :: 3 - Alpha
Classifier: Intended Audience :: Developers
Classifier: Topic :: Scientific/Engineering :: Artificial Intelligence
Classifier: License :: OSI Approved :: MIT License
Classifier: Programming Language :: Python :: 3
Requires-Dist: requests
Requires-Dist: matplotlib
Requires-Dist: psutil
Requires-Dist: pandas
Requires-Dist: numpy
Requires-Dist: scipy
Requires-Dist: lightgbm
Requires-Dist: lightfm
Requires-Dist: implicit
Requires-Dist: scikit-learn
Requires-Dist: sklearn-pandas
